PySieveEra/__init__.py
PySieveEra-0.1.dist-info/LICENCE.txt
PySieveEra-0.1.dist-info/METADATA
PySieveEra-0.1.dist-info/WHEEL
PySieveEra-0.1.dist-info/top_level.txt
PySieveEra-0.1.dist-info/RECORD
