Metadata-Version: 2.1
Name: PySieveEra
Version: 0.1
Summary: Generate a list of prime numbers within a specified range
Home-page: https://pypi.org/project/PySieveEra/
Author: Md. Ismiel Hossen Abir
License: MIT
License-File: LICENCE.txt
